bar_gmail/__init__.py
bar_gmail/app.py
bar_gmail/client_secrets.json
bar_gmail/gmail.py
bar_gmail/gmail_icon.svg
bar_gmail/printer.py
bar_gmail-1.0.6.dist-info/LICENSE
bar_gmail-1.0.6.dist-info/METADATA
bar_gmail-1.0.6.dist-info/WHEEL
bar_gmail-1.0.6.dist-info/entry_points.txt
bar_gmail-1.0.6.dist-info/RECORD
