Metadata-Version: 2.1
Name: bar-gmail
Version: 1.0.6
Summary: Get notifications and unread messages count from Gmail (Waybar/Polybar module)
Home-page: https://github.com/crabvk/bar-gmail
License: MIT
Keywords: waybar,polybar,gmail
Author: Vyacheslav Konovalov
Author-email: crabvk@protonmail.com
Requires-Python: >=3.10.7,<4.0.0
Classifier: Environment :: Console
Classifier: License :: OSI Approved :: MIT License
Classifier: Operating System :: OS Independent
Classifier: Programming Language :: Python :: 3
Classifier: Programming Language :: Python :: 3.11
Classifier: Programming Language :: Python :: 3.12
Requires-Dist: dasbus (>=1.7,<2.0)
Requires-Dist: google-api-python-client (>=2.155.0,<3.0.0)
Requires-Dist: google-auth-httplib2 (>=0.2.0,<0.3.0)
Requires-Dist: google-auth-oauthlib (>=1.1.0,<2.0.0)
Requires-Dist: pygobject (>=3.46.0,<4.0.0)
